oxapay_api/AsyncOxaPay.py
oxapay_api/SyncOxaPay.py
oxapay_api/__init__.py
oxapay_api/clients/AsyncClient.py
oxapay_api/clients/SyncClient.py
oxapay_api/clients/__init__.py
oxapay_api/clients/constants/__init__.py
oxapay_api/clients/constants/api_constants.py
oxapay_api/utils/__init__.py
oxapay_api/utils/response_models.py
oxapay_api-1.1.5.dist-info/METADATA
oxapay_api-1.1.5.dist-info/WHEEL
oxapay_api-1.1.5.dist-info/top_level.txt
oxapay_api-1.1.5.dist-info/RECORD
